rey/_version.py
rey/example.py
rey/py.typed
rey_py-0.0.0.dist-info/licenses/LICENSE
rey_py-0.0.0.dist-info/METADATA
rey_py-0.0.0.dist-info/WHEEL
rey_py-0.0.0.dist-info/top_level.txt
rey_py-0.0.0.dist-info/RECORD
